ikt/__init__.py
ikt/cli.py
ikt-0.2.0.dist-info/LICENSE
ikt-0.2.0.dist-info/METADATA
ikt-0.2.0.dist-info/WHEEL
ikt-0.2.0.dist-info/entry_points.txt
ikt-0.2.0.dist-info/top_level.txt
ikt-0.2.0.dist-info/RECORD
