Metadata-Version: 2.1
Name: ikt
Version: 0.2.0
Summary: Python tool to detect image content and make tags suggestions.
Home-page: https://github.com/insspb/ikt
Author: Andrey Shpak
Author-email: ashpak@ashpak.ru
License: MIT
Keywords: image-recognition,image-classification,image-analysis,image-annotation-tool,image-recognition-tool,image,keywords,tags,recognition,classification,tool
Platform: UNKNOWN
Classifier: Development Status :: 1 - Planning
Classifier: Environment :: Console
Classifier: Intended Audience :: Developers
Classifier: Intended Audience :: End Users/Desktop
Classifier: Intended Audience :: Information Technology
Classifier: Intended Audience :: Other Audience
Classifier: Topic :: Multimedia
Classifier: Topic :: Multimedia :: Graphics
Classifier: Operating System :: Microsoft :: Windows
Classifier: Operating System :: MacOS
Classifier: Operating System :: POSIX :: Linux
Classifier: Natural Language :: English
Classifier: License :: OSI Approved :: MIT License
Classifier: Programming Language :: Python
Classifier: Programming Language :: Python :: 3
Classifier: Programming Language :: Python :: 3 :: Only
Classifier: Programming Language :: Python :: 3.7
Classifier: Programming Language :: Python :: 3.8
Classifier: Programming Language :: Python :: Implementation :: CPython
Classifier: Topic :: Scientific/Engineering :: Image Recognition
Requires-Python: >=3.7
Requires-Dist: click (>=7.1.0)
